ros2_mypypkg/__init__.py
ros2_mypypkg/ros2_init.py
ros2_mypypkg-0.1.0.dist-info/WHEEL
ros2_mypypkg-0.1.0.dist-info/METADATA
ros2_mypypkg-0.1.0.dist-info/RECORD
