Metadata-Version: 2.1
Name: ros2-mypypkg
Version: 0.1.0
Summary: ros2_py_learn
Author: NopTop
Author-email: 439964032@qq.com
Requires-Python: >=3.10,<4.0
Classifier: Programming Language :: Python :: 3
Classifier: Programming Language :: Python :: 3.10
